[
{"LMOTOR":0,"RMOTOR":0,"ALTITUDE":72,"TEMPERATURE":24.16,"PRESSURE":1010.58},
{"LMOTOR":0,"RMOTOR":0,"ALTITUDE":72,"TEMPERATURE":24.16,"PRESSURE":1010.58},
{"LMOTOR":0,"RMOTOR":0,"ALTITUDE":72,"TEMPERATURE":24.16,"PRESSURE":1010.58},
{"LMOTOR":0,"RMOTOR":0,"ALTITUDE":72,"TEMPERATURE":24.16,"PRESSURE":1010.53},
{"LMOTOR":0,"RMOTOR":0,"ALTITUDE":72,"TEMPERATURE":24.16,"PRESSURE":1010.53},
{"LMOTOR":0,"RMOTOR":0,"ALTITUDE":72,"TEMPERATURE":24.17,"PRESSURE":1010.55},
{"LMOTOR":0,"RMOTOR":0,"ALTITUDE":72,"TEMPERATURE":24.17,"PRESSURE":1010.55},
{"LMOTOR":0,"RMOTOR":0,"ALTITUDE":72,"TEMPERATURE":24.16,"PRESSURE":1010.58},
{"LMOTOR":0,"RMOTOR":0,"ALTITUDE":72,"TEMPERATURE":24.16,"PRESSURE":1010.58},
{"LMOTOR":0,"RMOTOR":0,"ALTITUDE":72,"TEMPERATURE":24.16,"PRESSURE":1010.53},
{"LMOTOR":0,"RMOTOR":0,"ALTITUDE":72,"TEMPERATURE":24.16,"PRESSURE":1010.53},
{"LMOTOR":0,"RMOTOR":0,"ALTITUDE":72,"TEMPERATURE":24.16,"PRESSURE":1010.58},
{"LMOTOR":0,"RMOTOR":0,"ALTITUDE":72,"TEMPERATURE":24.16,"PRESSURE":1010.58},
{"LMOTOR":0,"RMOTOR":0,"ALTITUDE":72,"TEMPERATURE":24.16,"PRESSURE":1010.48},
{"LMOTOR":0,"RMOTOR":0,"ALTITUDE":72,"TEMPERATURE":24.16,"PRESSURE":1010.48},
{"LMOTOR":0,"RMOTOR":0,"ALTITUDE":72,"TEMPERATURE":24.16,"PRESSURE":1010.55},
{"LMOTOR":0,"RMOTOR":0,"ALTITUDE":72,"TEMPERATURE":24.16,"PRESSURE":1010.55},
{"LMOTOR":0,"RMOTOR":0,"ALTITUDE":72,"TEMPERATURE":24.14,"PRESSURE":1010.54},
{"LMOTOR":0,"RMOTOR":0,"ALTITUDE":72,"TEMPERATURE":24.14,"PRESSURE":1010.54},
{"LMOTOR":0,"RMOTOR":0,"ALTITUDE":72,"TEMPERATURE":24.14,"PRESSURE":1010.51},
{"LMOTOR":0,"RMOTOR":0,"ALTITUDE":72,"TEMPERATURE":24.14,"PRESSURE":1010.51},
{"LMOTOR":0,"RMOTOR":0,"ALTITUDE":72,"TEMPERATURE":24.18,"PRESSURE":1010.57},
{"LMOTOR":0,"RMOTOR":0,"ALTITUDE":72,"TEMPERATURE":24.18,"PRESSURE":1010.57},
{"LMOTOR":0,"RMOTOR":0,"ALTITUDE":72,"TEMPERATURE":24.16,"PRESSURE":1010.44},
{"LMOTOR":0,"RMOTOR":0,"ALTITUDE":72,"TEMPERATURE":24.16,"PRESSURE":1010.44},
{"LMOTOR":0,"RMOTOR":0,"ALTITUDE":72,"TEMPERATURE":24.14,"PRESSURE":1010.52},
{"LMOTOR":0,"RMOTOR":0,"ALTITUDE":72,"TEMPERATURE":24.14,"PRESSURE":1010.52},
{"LMOTOR":160,"RMOTOR":160,"ALTITUDE":74,"TEMPERATURE":24.14,"PRESSURE":1010.5},
{"LMOTOR":160,"RMOTOR":160,"ALTITUDE":74,"TEMPERATURE":24.14,"PRESSURE":1010.5},
{"LMOTOR":160,"RMOTOR":160,"ALTITUDE":74,"TEMPERATURE":24.14,"PRESSURE":1010.47},
{"LMOTOR":160,"RMOTOR":160,"ALTITUDE":73,"TEMPERATURE":24.14,"PRESSURE":1010.47},
{"LMOTOR":160,"RMOTOR":160,"ALTITUDE":74,"TEMPERATURE":24.16,"PRESSURE":1010.49},
{"LMOTOR":160,"RMOTOR":160,"ALTITUDE":74,"TEMPERATURE":24.16,"PRESSURE":1010.49},
{"LMOTOR":160,"RMOTOR":160,"ALTITUDE":74,"TEMPERATURE":24.14,"PRESSURE":1010.46},
{"LMOTOR":160,"RMOTOR":160,"ALTITUDE":74,"TEMPERATURE":24.14,"PRESSURE":1010.46},
{"LMOTOR":160,"RMOTOR":160,"ALTITUDE":74,"TEMPERATURE":24.14,"PRESSURE":1010.47},
{"LMOTOR":160,"RMOTOR":160,"ALTITUDE":74,"TEMPERATURE":24.14,"PRESSURE":1010.47},
{"LMOTOR":160,"RMOTOR":160,"ALTITUDE":74,"TEMPERATURE":24.14,"PRESSURE":1010.49},
{"LMOTOR":160,"RMOTOR":160,"ALTITUDE":73,"TEMPERATURE":24.14,"PRESSURE":1010.49},
{"LMOTOR":160,"RMOTOR":160,"ALTITUDE":74,"TEMPERATURE":24.14,"PRESSURE":1010.46},
{"LMOTOR":160,"RMOTOR":160,"ALTITUDE":74,"TEMPERATURE":24.14,"PRESSURE":1010.46},
{"LMOTOR":160,"RMOTOR":160,"ALTITUDE":74,"TEMPERATURE":24.14,"PRESSURE":1010.52},
{"LMOTOR":160,"RMOTOR":160,"ALTITUDE":74,"TEMPERATURE":24.14,"PRESSURE":1010.52},
{"LMOTOR":160,"RMOTOR":160,"ALTITUDE":74,"TEMPERATURE":24.14,"PRESSURE":1010.54},
{"LMOTOR":160,"RMOTOR":160,"ALTITUDE":74,"TEMPERATURE":24.14,"PRESSURE":1010.54},
{"LMOTOR":160,"RMOTOR":160,"ALTITUDE":74,"TEMPERATURE":24.14,"PRESSURE":1010.57},
{"LMOTOR":160,"RMOTOR":160,"ALTITUDE":73,"TEMPERATURE":24.14,"PRESSURE":1010.57},
{"LMOTOR":160,"RMOTOR":160,"ALTITUDE":74,"TEMPERATURE":24.14,"PRESSURE":1010.57},
{"LMOTOR":160,"RMOTOR":160,"ALTITUDE":74,"TEMPERATURE":24.14,"PRESSURE":1010.57},
{"LMOTOR":160,"RMOTOR":160,"ALTITUDE":74,"TEMPERATURE":24.14,"PRESSURE":1010.46},
{"LMOTOR":160,"RMOTOR":160,"ALTITUDE":74,"TEMPERATURE":24.14,"PRESSURE":1010.46},
{"LMOTOR":160,"RMOTOR":160,"ALTITUDE":73,"TEMPERATURE":24.13,"PRESSURE":1010.57},
{"LMOTOR":158,"RMOTOR":158,"ALTITUDE":74,"TEMPERATURE":24.13,"PRESSURE":1010.57},
{"LMOTOR":156,"RMOTOR":156,"ALTITUDE":73,"TEMPERATURE":24.14,"PRESSURE":1010.56},
{"LMOTOR":154,"RMOTOR":154,"ALTITUDE":73,"TEMPERATURE":24.14,"PRESSURE":1010.56},
{"LMOTOR":152,"RMOTOR":152,"ALTITUDE":73,"TEMPERATURE":24.14,"PRESSURE":1010.55},
{"LMOTOR":150,"RMOTOR":150,"ALTITUDE":73,"TEMPERATURE":24.14,"PRESSURE":1010.55},
{"LMOTOR":148,"RMOTOR":148,"ALTITUDE":73,"TEMPERATURE":24.14,"PRESSURE":1010.55},
{"LMOTOR":146,"RMOTOR":146,"ALTITUDE":73,"TEMPERATURE":24.14,"PRESSURE":1010.55},
{"LMOTOR":144,"RMOTOR":144,"ALTITUDE":73,"TEMPERATURE":24.14,"PRESSURE":1010.55},
{"LMOTOR":142,"RMOTOR":142,"ALTITUDE":73,"TEMPERATURE":24.14,"PRESSURE":1010.55},
{"LMOTOR":140,"RMOTOR":140,"ALTITUDE":73,"TEMPERATURE":24.16,"PRESSURE":1010.62},
{"LMOTOR":138,"RMOTOR":138,"ALTITUDE":74,"TEMPERATURE":24.16,"PRESSURE":1010.62},
{"LMOTOR":136,"RMOTOR":136,"ALTITUDE":74,"TEMPERATURE":24.14,"PRESSURE":1010.58},
{"LMOTOR":134,"RMOTOR":134,"ALTITUDE":73,"TEMPERATURE":24.14,"PRESSURE":1010.58},
{"LMOTOR":132,"RMOTOR":132,"ALTITUDE":73,"TEMPERATURE":24.16,"PRESSURE":1010.56},
{"LMOTOR":130,"RMOTOR":130,"ALTITUDE":73,"TEMPERATURE":24.16,"PRESSURE":1010.56},
{"LMOTOR":109,"RMOTOR":109,"ALTITUDE":73,"TEMPERATURE":24.16,"PRESSURE":1010.61},
{"LMOTOR":69,"RMOTOR":69,"ALTITUDE":72,"TEMPERATURE":24.16,"PRESSURE":1010.61},
{"LMOTOR":29,"RMOTOR":29,"ALTITUDE":72,"TEMPERATURE":24.16,"PRESSURE":1010.6},
{"LMOTOR":0,"RMOTOR":0,"ALTITUDE":72,"TEMPERATURE":24.16,"PRESSURE":1010.6},
{"LMOTOR":0,"RMOTOR":0,"ALTITUDE":72,"TEMPERATURE":24.16,"PRESSURE":1010.58},
{"LMOTOR":0,"RMOTOR":0,"ALTITUDE":72,"TEMPERATURE":24.16,"PRESSURE":1010.58},
{"LMOTOR":0,"RMOTOR":0,"ALTITUDE":72,"TEMPERATURE":24.14,"PRESSURE":1010.64},
{"LMOTOR":0,"RMOTOR":0,"ALTITUDE":72,"TEMPERATURE":24.14,"PRESSURE":1010.64},
{"LMOTOR":0,"RMOTOR":0,"ALTITUDE":72,"TEMPERATURE":24.18,"PRESSURE":1010.62},
{"LMOTOR":0,"RMOTOR":0,"ALTITUDE":72,"TEMPERATURE":24.18,"PRESSURE":1010.62},
{"LMOTOR":180,"RMOTOR":180,"ALTITUDE":72,"TEMPERATURE":24.17,"PRESSURE":1010.59},
{"LMOTOR":180,"RMOTOR":180,"ALTITUDE":85,"TEMPERATURE":24.17,"PRESSURE":1010.59},
{"LMOTOR":180,"RMOTOR":180,"ALTITUDE":110,"TEMPERATURE":24.19,"PRESSURE":1010.65}

]